llama_index/storage/kvstore/firestore/__init__.py
llama_index/storage/kvstore/firestore/base.py
llama_index_storage_kvstore_firestore-0.5.1.dist-info/METADATA
llama_index_storage_kvstore_firestore-0.5.1.dist-info/WHEEL
llama_index_storage_kvstore_firestore-0.5.1.dist-info/licenses/LICENSE
llama_index_storage_kvstore_firestore-0.5.1.dist-info/RECORD
